aws_message/VERSION
aws_message/__init__.py
aws_message/crypto.py
aws_message/gather.py
aws_message/message.py
aws_message/mock_sqs.py
aws_message/processor.py
aws_message/sqs.py
aws_message/test.py
aws_message/tests/__init__.py
aws_message/tests/test_message.py
aws_message/tests/test_processor.py
aws_message/tests/test_sqs.py
django_aws_message-1.5.4.dist-info/LICENSE
django_aws_message-1.5.4.dist-info/METADATA
django_aws_message-1.5.4.dist-info/WHEEL
django_aws_message-1.5.4.dist-info/top_level.txt
django_aws_message-1.5.4.dist-info/RECORD
